Metadata-Version: 2.1
Name: odoo14-addon-sale_backorder
Version: 14.0.1.0.1.dev13
Summary: Report of Un-Invoice Goods Delivered and Backorders
Home-page: https://github.com/OCA/sale-reporting
Author: Open Source Integrators, Odoo Community Association (OCA)
Author-email: support@odoo-community.org
License: LGPL-3
Classifier: Programming Language :: Python
Classifier: Framework :: Odoo
Classifier: Framework :: Odoo :: 14.0
Classifier: License :: OSI Approved :: GNU Lesser General Public License v3 (LGPLv3)
Classifier: Development Status :: 4 - Beta
Requires-Python: >=3.6
Requires-Dist: odoo<14.1dev,>=14.0a
